LICENSE
MANIFEST.in
README.rst
requirements.txt
setup.py
src/plugify/__init__.py
src/plugify/client.py
src/plugify/dispatch.py
src/plugify/enums.py
src/plugify/gateway.py
src/plugify/group.py
src/plugify/http.py
src/plugify/py.typed
src/plugify/user.py
src/plugify.py.egg-info/PKG-INFO
src/plugify.py.egg-info/SOURCES.txt
src/plugify.py.egg-info/dependency_links.txt
src/plugify.py.egg-info/requires.txt
src/plugify.py.egg-info/top_level.txt
src/plugify/types/__init__.py
src/plugify/types/snowflake.py